fastopp/__init__.py
fastopp-0.4.7.dist-info/METADATA
fastopp-0.4.7.dist-info/WHEEL
fastopp-0.4.7.dist-info/entry_points.txt
fastopp-0.4.7.dist-info/licenses/LICENSE
fastopp-0.4.7.dist-info/RECORD
