Metadata-Version: 2.4
Name: fastopp
Version: 0.4.7
Summary: FastAPI opinionated stack inspired by Django for students prototyping AI web applications. Authentication, database, admin panel, HTML templates, and more.
Author: Oppkey
License-File: LICENSE
Requires-Python: >=3.12
Requires-Dist: aiohttp>=3.13.1
Requires-Dist: aiosqlite>=0.21.0
Requires-Dist: alembic>=1.17.0
Requires-Dist: boto3>=1.40.55
Requires-Dist: fastapi-users[sqlalchemy]>=14.0.1
Requires-Dist: fastapi>=0.119.1
Requires-Dist: hatchling>=1.27.0
Requires-Dist: httpx>=0.28.1
Requires-Dist: itsdangerous>=2.2.0
Requires-Dist: jinja2>=3.1.6
Requires-Dist: markdown>=3.8.2
Requires-Dist: psycopg[binary]>=3.2.11
Requires-Dist: pydantic-settings>=2.11.0
Requires-Dist: pyjwt>=2.10.1
Requires-Dist: python-dotenv>=1.1.1
Requires-Dist: requests>=2.31.0
Requires-Dist: sqladmin>=0.21.0
Requires-Dist: sqlalchemy>=2.0.44
Requires-Dist: sqlmodel>=0.0.27
Requires-Dist: sse-starlette>=3.0.2
Requires-Dist: twine>=6.2.0
Requires-Dist: uvicorn>=0.38.0
